pts1_prediction_tool/__init__.py
pts1_prediction_tool/pts1_prediction.py
pts1_prediction_tool/datasets/pts1_filtered_peroxisomal_sequences.fasta
pts1_prediction_tool/datasets/raw_non_peroxisomal_sequences.fasta
pts1_prediction_tool/datasets/raw_peroxisomal_sequences.fasta
pts1_prediction_tool-1.0.2.dist-info/LICENSE
pts1_prediction_tool-1.0.2.dist-info/METADATA
pts1_prediction_tool-1.0.2.dist-info/WHEEL
pts1_prediction_tool-1.0.2.dist-info/top_level.txt
pts1_prediction_tool-1.0.2.dist-info/RECORD
