Metadata-Version: 2.1
Name: pts1-prediction-tool
Version: 1.0.2
Summary: Tool for predicting a PTS1 (peroxisomal targeting sequence 1) in a amino acid sequence.
Home-page: https://github.com/oKoch/pts1-prediction-tool
Author: Oliver Koch
Author-email: ollis.lab@gmail.com
License: BSD-3
Keywords: pts1,pts1-prediction,pts1_prediction_tool
Platform: UNKNOWN
Requires-Python: >=3.6
Requires-Dist: numpy
Requires-Dist: bio
Requires-Dist: pandas
Requires-Dist: sklearn
Requires-Dist: openpyxl
